chibi_api/__init__.py
chibi_api/chibi_api.py
chibi_api-0.1.0.dist-info/AUTHORS.rst
chibi_api-0.1.0.dist-info/LICENSE
chibi_api-0.1.0.dist-info/METADATA
chibi_api-0.1.0.dist-info/WHEEL
chibi_api-0.1.0.dist-info/top_level.txt
chibi_api-0.1.0.dist-info/RECORD
