Metadata-Version: 2.2
Name: chibi_api
Version: 0.1.0
Summary: libreria para hacer clientes de apis rest
Home-page: https://github.com/dem4ply/chibi_api
Author: dem4ply
Author-email: dem4ply@gmail.com
License: WTFPL
Keywords: chibi_api
Classifier: Development Status :: 2 - Pre-Alpha
Classifier: Intended Audience :: Developers
Classifier: License :: Public Domain
Classifier: Natural Language :: English
Classifier: Programming Language :: Python :: 3.7
Classifier: Programming Language :: Python :: 3.8
License-File: LICENSE
License-File: AUTHORS.rst
Requires-Dist: chibi_hybrid>=1.2.0
Requires-Dist: chibi_requests>=1.3.0
Dynamic: author
Dynamic: author-email
Dynamic: classifier
Dynamic: description
Dynamic: home-page
Dynamic: keywords
Dynamic: license
Dynamic: requires-dist
Dynamic: summary
